pabtc/__init__.py
pabtc/base58.py
pabtc/bech32.py
pabtc/config.py
pabtc/core.py
pabtc/denomination.py
pabtc/ecdsa.py
pabtc/objectdict.py
pabtc/opcode.py
pabtc/rate.py
pabtc/ripemd160.py
pabtc/rpc.py
pabtc/schnorr.py
pabtc/secp256k1.py
pabtc/wallet.py
pabtc-1.2.3.dist-info/METADATA
pabtc-1.2.3.dist-info/WHEEL
pabtc-1.2.3.dist-info/licenses/LICENSE
pabtc-1.2.3.dist-info/RECORD
