Metadata-Version: 2.4
Name: pabtc
Version: 1.2.3
Summary: Plbtc: bitcoin library for humans
Project-URL: homepage, https://github.com/mohanson/pabtc
Author-email: Mohanson <mohanson@outlook.com>
License: MIT License
License-File: LICENSE
Requires-Dist: requests
